{
    "employments": [
        {
            "img": "https://firebasestorage.googleapis.com/v0/b/images-cdwenz.appspot.com/o/technologies%2Femploy_ivoy.png?alt=media&token=917e97a5-f79e-4675-97ea-71f19f25e4d9",
            "title": "ivoy - tus envíos mas rápidos",
            "date": "2022 - 2023",
            "details": [
                "Distribución equilibrada de tareas",
                "Integración de clientes a nuestra API",
                "Desarrollar procesos documentados",
                "Implementar estrategia de atención de incidencias y requerimientos",
                "Seguimiento de primer contacto a incidencias y requerimientos realizadospor usuarios finales.", 
                "A cargo del sistema de tickets."
            ],
            "position": "Head of integrations & support"
        },
        {
            "img": "https://firebasestorage.googleapis.com/v0/b/images-cdwenz.appspot.com/o/technologies%2Femploy_ivoy.png?alt=media&token=917e97a5-f79e-4675-97ea-71f19f25e4d9",
            "title": "ivoy - tus envíos mas rápidos",
            "date": "2022 - 2023",
            "details": [
                "Distribución equilibrada de tareas",
                "Integración de clientes a nuestra API",
                "Desarrollar procesos documentados",
                "Implementar estrategia de atención de incidencias y requerimientos",
                "Seguimiento de primer contacto a incidencias y requerimientos realizadospor usuarios finales.", 
                "A cargo del sistema de tickets."
            ],
            "position": "Head of integrations & support"
        },
        {
            "img": "https://firebasestorage.googleapis.com/v0/b/images-cdwenz.appspot.com/o/technologies%2Femploy_ivoy.png?alt=media&token=917e97a5-f79e-4675-97ea-71f19f25e4d9",
            "title": "ivoy - tus envíos mas rápidos",
            "date": "2022 - 2023",
            "details": [
                "Distribución equilibrada de tareas",
                "Integración de clientes a nuestra API",
                "Desarrollar procesos documentados",
                "Implementar estrategia de atención de incidencias y requerimientos",
                "Seguimiento de primer contacto a incidencias y requerimientos realizadospor usuarios finales.", 
                "A cargo del sistema de tickets."
            ],
            "position": "Head of integrations & support"
        },
        {
            "img": "https://firebasestorage.googleapis.com/v0/b/images-cdwenz.appspot.com/o/technologies%2Femploy_ivoy.png?alt=media&token=917e97a5-f79e-4675-97ea-71f19f25e4d9",
            "title": "ivoy - tus envíos mas rápidos",
            "date": "2022 - 2023",
            "details": [
                "Distribución equilibrada de tareas",
                "Integración de clientes a nuestra API",
                "Desarrollar procesos documentados",
                "Implementar estrategia de atención de incidencias y requerimientos",
                "Seguimiento de primer contacto a incidencias y requerimientos realizadospor usuarios finales.", 
                "A cargo del sistema de tickets."
            ],
            "position": "Head of integrations & support"
        }
    ]
}